{
  "created_at": "Tue Jul 09 19:53:35 +0000 2013",
  "deleted": true,
  "favorite_count": 3138,
  "hashtags": [],
  "id": 354689810528604160,
  "id_str": "354689810528604160",
  "lang": "en",
  "legacy_imported": true,
  "retrieved": "2017-04-28--00-07-07",
  "retweet_count": 4210,
  "source": "<a href=\"http://twitter.com\" rel=\"nofollow\">Twitter Web Client</a>",
  "text": "The final version will be ready within the next week.",
  "urls": [],
  "user": {
    "id": 169686021
  },
  "user_mentions": []
}