{
  "created_at": "Fri Feb 20 15:47:19 +0000 2015",
  "deleted": true,
  "favorite_count": 9515,
  "hashtags": [],
  "id": 568799064843685888,
  "id_str": "568799064843685888",
  "lang": "en",
  "legacy_imported": true,
  "retrieved": "2017-04-28--00-07-07",
  "retweet_count": 5003,
  "source": "<a href=\"http://twitter.com\" rel=\"nofollow\">Twitter Web Client</a>",
  "text": "and I have encountered countless amounts of bigotry along the way.",
  "urls": [],
  "user": {
    "id": 169686021
  },
  "user_mentions": []
}