{
  "created_at": "Mon Mar 02 02:42:32 +0000 2015",
  "deleted": true,
  "favorite_count": 20032,
  "hashtags": [],
  "id": 572225445325873154,
  "id_str": "572225445325873154",
  "lang": "en",
  "legacy_imported": true,
  "retrieved": "2017-04-28--00-07-07",
  "retweet_count": 11170,
  "source": "<a href=\"http://twitter.com\" rel=\"nofollow\">Twitter Web Client</a>",
  "text": "HAPPY BDAY TO MY BROTHER MIKE DEAN, MIKE YOU’RE ONE OF THE GREATEST LIVING MUSICIANS IF NOT THE GREATEST",
  "urls": [],
  "user": {
    "id": 169686021
  },
  "user_mentions": []
}