{
  "created_at": "Wed Feb 17 17:35:17 +0000 2016",
  "deleted": true,
  "favorite_count": 92883,
  "hashtags": [],
  "id": 700010641730437120,
  "id_str": "700010641730437120",
  "lang": "en",
  "legacy_imported": true,
  "retrieved": "2017-04-28--00-07-06",
  "retweet_count": 79588,
  "source": "<a href=\"http://twitter.com/download/iphone\" rel=\"nofollow\">Twitter for iPhone</a>",
  "text": "A wise man should be humble enough to admit when he’s wrong and change his mind based on new information…",
  "urls": [],
  "user": {
    "id": 169686021
  },
  "user_mentions": []
}