{
  "created_at": "Wed Feb 17 17:35:42 +0000 2016",
  "deleted": true,
  "favorite_count": 46009,
  "hashtags": [],
  "id": 700010748555165696,
  "id_str": "700010748555165696",
  "lang": "en",
  "legacy_imported": true,
  "retrieved": "2017-04-28--00-07-06",
  "retweet_count": 25557,
  "source": "<a href=\"http://twitter.com/download/iphone\" rel=\"nofollow\">Twitter for iPhone</a>",
  "text": "There is so much positive energy right now …  Let’s stay on this Ultra Light Beam…",
  "urls": [],
  "user": {
    "id": 169686021
  },
  "user_mentions": []
}