{
  "created_at": "Wed Mar 09 23:27:36 +0000 2016",
  "deleted": true,
  "favorite_count": 24561,
  "hashtags": [],
  "id": 707709451298611200,
  "id_str": "707709451298611200",
  "lang": "en",
  "legacy_imported": true,
  "retrieved": "2017-04-28--00-07-06",
  "retweet_count": 7867,
  "source": "<a href=\"http://twitter.com\" rel=\"nofollow\">Twitter Web Client</a>",
  "text": "I like T-shirts and women in yoga pants… I live in LA that’s what people wear… not sure why someone would put a suit jacket on with that.",
  "urls": [],
  "user": {
    "id": 169686021
  },
  "user_mentions": []
}