{
  "created_at": "Sat Apr 02 21:31:13 +0000 2016",
  "deleted": true,
  "favorite_count": 73059,
  "hashtags": [],
  "id": 716377473387077635,
  "id_str": "716377473387077635",
  "lang": "en",
  "legacy_imported": true,
  "retrieved": "2017-04-28--00-07-06",
  "retweet_count": 26269,
  "source": "<a href=\"http://twitter.com\" rel=\"nofollow\">Twitter Web Client</a>",
  "text": "and also my number one design rule of anything I do from shoes to music to homes is that Kim has to like it....",
  "urls": [],
  "user": {
    "id": 169686021
  },
  "user_mentions": []
}